cell_fate/__init__.py
cell_fate-0.0.0.dist-info/LICENSE
cell_fate-0.0.0.dist-info/METADATA
cell_fate-0.0.0.dist-info/WHEEL
cell_fate-0.0.0.dist-info/top_level.txt
cell_fate-0.0.0.dist-info/RECORD
